{
  "attributes": {
    "raw": {
      "document": "---\ntitle: \"CUBA Ransomware Malware Analysis\"\nslug: \"cuba-ransomware-malware-analysis\"\ndate: \"2023-02-14\"\ndescription: \"Elastic Security has performed a deep technical analysis of the CUBA ransomware family. This includes malware capabilities as well as defensive countermeasures.\"\nauthor:\n  - slug: salim-bitam\nimage: \"blog-thumb-coin-stacks.jpg\"\ncategory:\n  - slug: malware-analysis\ntags:\n  - ref9019\n  - cuba\n  - ransomware\n---\n\n## Summary\n\nAs a part of Elastic Security’s ongoing threat detection and monitoring efforts, we have recently observed a ransomware intrusion by the CUBA ransomware threat group, internally tracked as REF9019. This report will detail the inner workings of the ransomware deployed inside the network to encrypt the victim’s files. Cuba ransomware provides the attacker with the flexibility to encrypt both local and network shares files in the enterprise. CUBA uses the ChaCha20 cipher algorithm for symmetric encryption and RSA encryption to protect the ChaCha20 keys. CUBA is multithreaded for faster encryption with resource access synchronization to avoid file corruption.\n\nIn this analysis we will describe the following:\n\n- Operations mode\n- Process and services termination\n- Enumeration of volumes\n- Threading implementation\n- File encryption and algorithms used\n- MITRE Attack mapping\n- YARA rule\n- Indicators of compromise\n\n### Static Analysis\n\n|                 |                                                                  |\n| --------------- | ---------------------------------------------------------------- | --- |\n| SHA256 Packed   | 0f385cc69a93abeaf84994e7887cb173e889d309a515b55b2205805bdfe468a3 |\n| SHA256 Unpacked | 3654af86dc682e95c811e4fd87ea405b627bca81c656f3a520a4b24bf2de879f |\n| File Size       | 135168 bytes                                                     |\n| FileType:       | Executable                                                       |\n| Imphash:        | CA5F4AF10ABC885182F3FB9ED425DE65                                 |\n| Compile Time    | Wed Mar 09 22:00:31 2022                                         | UTC |\n| Entropy         | 6.582                                                            |\n\n### Sections\n\n|        |                |              |          |         |                                  |\n| ------ | -------------- | ------------ | -------- | ------- | -------------------------------- |\n| Name   | VirtualAddress | Virtual Size | Raw Size | Entropy | MD5                              |\n| .text  | 0x00401000     | 0x13B5F      | 0x13C00  | 6.608   | 931B22064E9E214BF59A4E07A6CA9109 |\n| .rdata | 0x00415000     | 0xA71C       | 0xA800   | 5.855   | F6F97411BCD64126A96B08BA9AE1E775 |\n| .data  | 0x00420000     | 0x16B0       | 0xC00    | 3.450   | 03B1B11B4531BB656E43A8B457D4A5F7 |\n| .rsrc  | 0x00422000     | 0x1E0        | 0x200    | 4.704   | F754ADBD7F5D6195FD6D527001CAB98C |\n| .reloc | 0x00423000     | 0x1200       | 0x1200   | 6.573   | 08B0994DAECAAAA4173B388A80CC52FE |\n\n> For information on the CUBA ransomware campaign and associated malware analysis, check out our blog posts detailing this:\n>\n> - [CUBA Campaign Analysis](https://www.elastic.co/security-labs/cuba-ransomware-malware-analysis)\n> - [BUGHATCH Malware Analysis](https://www.elastic.co/security-labs/bughatch-malware-analysis)\n\n### Imports\n\n```\nGetProcessImageFileNameW\nEnumProcesses\nNetApiBufferFree\nNetShareEnum\nGetIpNetTable\nPathFindFileNameW\nFindFirstFileExW\nFindFirstFileW\nFindNextFileW\nWriteFile\nSetFileAttributesW\nMoveFileExW\nFindFirstVolumeW\nTerminateProcess\nGetEnvironmentStringsW\nOpenProcess\nGetCurrentProcessId\nCreateProcessW\nGetVolumePathNamesForVolumeNameW\nFindNextVolumeW\nGetCurrentThreadId\nRaiseException\nGetModuleHandleExW\nOpenProcessToken\nCryptAcquireContextA\nCryptGenRandom\nCryptReleaseContext\nAdjustTokenPrivileges\nLookupPrivilegeValueA\nControlService\nChangeServiceConfigW\nPathAddBackslashW\nGetCPInfo\nGetOEMCP\nIsValidCodePage\nlstrcpynW\nInterlockedDecrement\nFindClose\nCreateFileW\nSleep\nlstrcatW\nCloseHandle\nCreateThread\nlstrcpyW\nlstrcmpW\nReadFile\nGetFileSizeEx\nEnterCriticalSection\nGetCurrentProcess\nGetModuleFileNameW\nLeaveCriticalSection\nGetCommandLineA\nWaitForSingleObject\nGetLastError\nSetEvent\nGetDiskFreeSpaceExW\nResetEvent\nGetWindowsDirectoryW\nSetFilePointerEx\nExitProcess\nCreateEventA\nlstrcmpiW\nGetTickCount\nDeleteCriticalSection\nQueryPerformanceCounter\nSetStdHandle\nFreeEnvironmentStringsW\nGetCommandLineW\nDecodePointer\nGetStringTypeW\nGetProcessHeap\nFlushFileBuffers\nGetConsoleCP\nHeapSize\nWriteConsoleW\nInitializeCriticalSection\nUnhandledExceptionFilter\nSetUnhandledExceptionFilter\nIsProcessorFeaturePresent\nInitializeCriticalSectionAndSpinCount\nWaitForSingleObjectEx\nCreateEventW\nGetModuleHandleW\nGetProcAddress\nIsDebuggerPresent\nGetStartupInfoW\nGetSystemTimeAsFileTime\nInitializeSListHead\nRtlUnwind\nSetLastError\nEncodePointer\nTlsAlloc\nTlsGetValue\nTlsSetValue\nTlsFree\nFreeLibrary\nLoadLibraryExW\nGetFileType\nGetStdHandle\nMultiByteToWideChar\nWideCharToMultiByte\nGetACP\nHeapFree\nHeapAlloc\nLCMapStringW\nHeapReAlloc\nGetConsoleMode\nCharLowerW\nGetKeyboardLayoutList\nwsprintfW\nCloseServiceHandle\nOpenSCManagerW\nOpenServiceW\nQueryServiceStatusEx\n```\n\n### Strings\n\n```\nGood day. All your files are encrypted. For decryption contact us.\nWrite here waterstatus@cock.li\nreserve admin@encryption-support.com\njabber cuba_support@exploit.im\nWe also inform that your databases, ftp server and file server were downloaded by us to our servers.\nIf we do not receive a message from you within three days, we regard this as a refusal to negotiate.\nCheck our platform: http://cuba4ikm4jakjgmkezytyawtdgr2xymvy6nvzgw5cglswg3si76icnqd.onion/\n* Do not rename encrypted files.\n* Do not try to decrypt your data using third party software,\n  it may cause permanent data loss.\n* Do not stop process of encryption, because partial encryption cannot be decrypted.\n!! READ ME !!.txt\n```\n\n## Code Analysis\n\n### Entry Point\n\nThe malware starts by retrieving the active input locale identifier of the victim using the GetKeyboardLayout API. When the Russian language is in the list of supported languages of the machine, the process deletes and terminates itself with a simple command line: c:\\system32\\cmd.exe c/ del PATH_TO_BINARY without encrypting the file system.\n\n![](/assets/images/cuba-ransomware-malware-analysis/image5-cuba-ransomware-elastic.jpg)\n\n### Command-line Options\n\nThe threat actor included 4 different operations based on the following command-line arguments:\n\n- The network keyword\n- An IP keyword\n- A path keyword\n- The local keyword\n  ![](/assets/images/cuba-ransomware-malware-analysis/image12-cuba-ransomware-elastic.jpg)\n\n**Network keyword parameter**\n\nWhen specifying the network keyword, the malware retrieves the Address Resolution Protocol (ARP) table of the machine using the GetIpNetTable Windows API and enumerates the shares of each IP in the ARP table, this information is added to a linked list that will be accessed by the encryption capability, which will be discussed further below in detail.\n\n![](/assets/images/cuba-ransomware-malware-analysis/image13-cuba-ransomware-elastic.jpg)\n\n**IP keyword parameter**\n\nBy specifying an IP address as the first parameter in the command line the malware proceeds by enumerating and encrypting every share found for the specified IP.\n\n**Path keyword parameter**\n\nThe malware will encrypt the local directory contents, or the file provided, as the first parameter of the command-line.\n\n**Local keyword parameter**\n\nThe local keyword is used to encrypt every local volume on the machine, and because the malware targets volumes by their ID, it can encrypt both mounted and unmounted volumes.\n\n### Process Termination\n\nCUBA starts by acquiring SeDebugPrivilege and then terminates a hardcoded list of processes and services using a common Windows API (see appendix for list [[1](https://www.elastic.co/security-labs/cuba-ransomware-malware-analysis#list-of-terminated-processes)], [[2](https://www.elastic.co/security-labs/cuba-ransomware-malware-analysis#list-of-terminated-services)]). For some services, the malware first tries to disable the service– indicated by the second parameter of TerminateProcesses::TerminateServiceByName function. This is mainly done to prevent interference with the encryption process by applications that may lock files from external changes, for example, databases.\n\n![](/assets/images/cuba-ransomware-malware-analysis/image8-cuba-ransomware-elastic.jpg)\n\n### Local Volume Enumeration\n\nThe malware enumerates all the local volumes and for each volume larger than 1GB it saves the volume’s GUID in a custom linked list. The ransomware utilizes the CriticalSection object to access this linked list for synchronization purposes due to multiple threads accessing the same resource. This helps to avoid two threads encrypting the same file at the same time, a race condition that would corrupt the file.\n\n![](/assets/images/cuba-ransomware-malware-analysis/image6-cuba-ransomware-elastic.jpg)\n\n![](/assets/images/cuba-ransomware-malware-analysis/image2-cuba-ransomware-elastic.jpg)\n\n### Multithreaded Encryption Synchronization\n\nAfter preparing a list to encrypt, CUBA ransomware spawns encryption threads with the structure defined below as a parameter. Depending on the command line arguments, the malware starts 4 threads for local encryption or 8 threads for network encryption.\n\n![](/assets/images/cuba-ransomware-malware-analysis/image10-cuba-ransomware-elastic.jpg)\n\nWhen a thread finishes its task, it will decrement a counter until it reaches 0: lpParameter-\\\\>NumberOfThreadRunning. When the last thread completes, it will alert the program that the task is done with a call to SetEvent API, which will self delete and terminate the malware.\n\n![](/assets/images/cuba-ransomware-malware-analysis/image11-cuba-ransomware-elastic.jpg)\n\n### Encryption Implementation\n\nThe malware leverages the symmetric encryption algorithm ChaCha20 to encrypt files and the asymmetric encryption algorithm RSA to protect the ChaCha20 Key and Initialization Vector (IV). The author has utilized a customized version of [WolfSSL](https://github.com/wolfSSL/wolfssl), an open source SSL/TLS library, to implement this capability. Other samples (2957226fc315f71dc22f862065fe376efab9c21d61bbc374dde34d47cde85658) implemented a similar function using the [libtomcrypt](https://github.com/libtom/libtomcrypt) library. Other implementations may exist that are not described here.\n\nThe ransomware allocates a large custom structure called block that contains all the required encryption information. It then initializes an RsaKey structure with [wc_InitRsaKey](https://www.wolfssl.com/doxygen/group__RSA.html#ga02c9b34d405c5f1c24956ee84a843ef6) and decodes an embedded 4096 bit RSA public key in [DER](https://wiki.openssl.org/index.php/DER) format using [wc_RsaPublicKeyDecode](https://www.wolfssl.com/doxygen/group__RSA.html#ga2610326206b322f33f59e31a845e24b9) which it saves to block.PubRsaKey.\n\n![](/assets/images/cuba-ransomware-malware-analysis/image7-cuba-ransomware-elastic.jpg)\n\n### File Enumeration\n\nEach thread takes an entry from the linked list and starts recursively enumerating files starting from the root of the volume. In the case of a specific directory, the same function is called recursively except for specific directories (see [appendix](https://www.elastic.co/security-labs/cuba-ransomware-malware-analysis#excluded-directories) for list). Otherwise, it will ignore the ransom note file !! READ ME !!.txt and files with specific extensions (see [appendix](https://www.elastic.co/security-labs/cuba-ransomware-malware-analysis#excluded-file-extensions) for list).\n\n![](/assets/images/cuba-ransomware-malware-analysis/image15-cuba-ransomware-elastic.jpg)\n\nThe malware uses [wc_RNG_GenerateBlock](https://www.wolfssl.com/doxygen/group__Random.html#ga9a289fb3f58f4a5f7e15c2b5a1b0d7c6) a WolfSSL function, to randomly generate 44 bytes. The first 32 bytes of that are used as the ChaCha20 key and the other 12 bytes are used as the IV, it then calls a function to initiate the ChaCha20 structure block.chacha20_KeyIv that will be later used to encrypt the file content. At this point, the ransomware is ready to start encrypting and writing to the file.\n\n![](/assets/images/cuba-ransomware-malware-analysis/image14-cuba-ransomware-elastic.jpg)\n\nBefore encrypting a file, Cuba ransomware prepends a 1024 byte header, the first 256 bytes are the string FIDEL.CA and some DWORD bytes values, the next 512 bytes are the encrypted ChaCha20 KEY/IV with the public RSA key and the rest is padded with 0.\n\n![](/assets/images/cuba-ransomware-malware-analysis/image3-cuba-ransomware-elastic.jpg)\n\nBefore starting the encryption, the malware double checks if the file was already encrypted by comparing the first 8 bytes of the file to the header string FIDEL.CA. If equal, the malware terminates the encryption process as described below.\n\n![](/assets/images/cuba-ransomware-malware-analysis/image16-cuba-ransomware-elastic.jpg)\n\nThen CUBA writes the 1024 byte header and if the file is larger than 2 MB it reads 1 MB of data at a time from the file and encrypts it with the ChaCha20 cipher. Otherwise, it will read and encrypt the entire contents at once.\n\n![](/assets/images/cuba-ransomware-malware-analysis/image1-cuba-ransomware-elastic.jpg)\n\nThe malware encrypts the file in 1 MB chunks and, depending on the file’s size, it will skip a preset number of bytes. This is done primarily to speed up the encryption process of large files, below is a table to illustrate.\n\n|                  |                      |              |\n| ---------------- | -------------------- | ------------ |\n| File Size        | Chunk Size           | Skipped Size |\n| Less than 2 MB   | All the file content | 0 MB         |\n| Less than 10 MB  | 1MB                  | 4 MB         |\n| Less than 50 MB  | 1MB                  | 8 MB         |\n| Less than 200 MB | 1MB                  | 16 MB        |\n| Less than 10 GB  | 1MB                  | 200 MB       |\n| More than 10 GB  | 1MB                  | 500 MB       |\n\nFinally, it will rename the file by adding the extension .cuba.\n\n![](/assets/images/cuba-ransomware-malware-analysis/image9-cuba-ransomware-elastic.jpg)\n\n![](/assets/images/cuba-ransomware-malware-analysis/image4-cuba-ransomware-elastic.jpg)\n\n## MITRE ATT&CK Techniques\n\nUsing the MITRE ATT&CK® framework, techniques and sub techniques represent how an adversary achieves a tactical goal by performing an action.\n\n- [Data Encrypted for Impact](https://attack.mitre.org/techniques/T1486/)\n- [Network Share Discovery](https://attack.mitre.org/techniques/T1135/)\n- [Process Discovery](https://attack.mitre.org/techniques/T1057/)\n- [Service Stop](https://attack.mitre.org/techniques/T1489/)\n- [System Information Discovery](https://attack.mitre.org/techniques/T1082/)\n- [Indicator Removal on Host: File Deletion](https://attack.mitre.org/techniques/T1070/004/)\n- [Obfuscated Files or Information: Software Packing](https://attack.mitre.org/techniques/T1027/002/)\n- [System Network Configuration Discovery](https://attack.mitre.org/techniques/T1016/)\n- [System Location Discovery: System Language Discovery](https://attack.mitre.org/techniques/T1614/001/)\n- [Data Encrypted for Impact](https://attack.mitre.org/techniques/T1486/)\n- [Access Token Manipulation](https://attack.mitre.org/techniques/T1134/)\n\n## Appendix\n\n### List of Terminated Processes\n\n- sqlagent.exe\n- sqlservr.exe\n- sqlwriter.exe\n- sqlceip.exe\n- msdtc.exe\n- sqlbrowser.exe\n- vmwp.exe\n- vmsp.exe\n- outlook.exe\n- Microsoft.Exchange.Store.Worker.exe\n\n### List of Terminated Services\n\n- MySQL\n- MySQL80\n- SQLSERVERAGENT\n- MSSQLSERVER\n- SQLWriter\n- SQLTELEMETRY\n- MSDTC\n- SQLBrowser\n- vmcompute\n- vmms\n- MSExchangeUMCR\n- MSExchangeUM\n- MSExchangeTransportLogSearch\n- MSExchangeTransport\n- MSExchangeThrottling\n- MSExchangeSubmission\n- MSExchangeServiceHost\n- MSExchangeRPC\n- MSExchangeRepl\n- MSExchangePOP3BE\n- MSExchangePop3\n- MSExchangeNotificationsBroker\n- MSExchangeMailboxReplication\n- MSExchangeMailboxAssistants\n- MSExchangeIS\n- MSExchangeIMAP4BE\n- MSExchangeImap4\n- MSExchangeHMRecovery\n- MSExchangeHM\n- MSExchangeFrontEndTransport\n- MSExchangeFastSearch\n- MSExchangeEdgeSync\n- MSExchangeDiagnostics\n- MSExchangeDelivery\n- MSExchangeDagMgmt\n- MSExchangeCompliance\n- MSExchangeAntispamUpdate\n\n### Excluded Directories\n\n- \\windows\\\n- \\program files\\microsoft office\\\n- \\program files (x86)\\microsoft office\\\n- \\program files\\avs\\\n- \\program files (x86)\\avs\\\n- \\$recycle.bin\\\n- \\boot\\\n- \\recovery\\\n- \\system volume information\\\n- \\msocache\\\n- \\users\\all users\\\n- \\users\\default user\\\n- \\users\\default\\\n- \\temp\\\n- \\inetcache\\\n- \\google\\\n\n### Excluded File Extensions\n\n- .exe\n- .dll\n- .sys\n- .ini\n- .lnk\n- .vbm\n- .cuba\n\n## YARA Rule\n\nElastic Security has created YARA rules to identify CUBA ransomware activity.\n\n```\nrule Windows_Ransomware_Cuba {\n    meta:\n        os = \"Windows\"\n        arch = \"x86\"\n        category_type = \"Ransomware\"\n        family = \"Cuba\"\n        threat_name = \"Windows.Ransomware.Cuba\"\n        Reference_sample = \"33352a38454cfc247bc7465bf177f5f97d7fd0bd220103d4422c8ec45b4d3d0e\"\n\n    strings:\n       $a1 = { 45 EC 8B F9 8B 45 14 89 45 F0 8D 45 E4 50 8D 45 F8 66 0F 13 }\n       $a2 = { 8B 06 81 38 46 49 44 45 75 ?? 81 78 04 4C 2E 43 41 74 }\n     $b1 = \"We also inform that your databases, ftp server and file server were downloaded by us to our     servers.\" ascii fullword\n       $b2 = \"Good day. All your files are encrypted. For decryption contact us.\" ascii fullword\n       $b3 = \".cuba\" wide fullword\n\n    condition:\n        any of ($a*) or all of ($b*)\n}\n```\n\n## Observations\n\nAtomic indicators observed in our investigation.\n\n|                                                                  |        |                 |\n| ---------------------------------------------------------------- | ------ | --------------- |\n| Indicator                                                        | Type   | Note            |\n| 32beefe2c5e28e87357813c0ef91f47b631a3dff4a6235256aa123fc77564346 | SHA256 | CUBA Ransomware |\n| 0f385cc69a93abeaf84994e7887cb173e889d309a515b55b2205805bdfe468a3 | SHA256 | CUBA Ransomware |\n| bcf0f202db47ca671ed6146040795e3c8315b7fb4f886161c675d4ddf5fdd0c4 | SHA256 | CUBA Ransomware |\n\n## Artifacts\n\nArtifacts are also available for download in both ECS and STIX format in a combined zip bundle.\n"
    },
    "title": "CUBA Ransomware Malware Analysis",
    "slug": "cuba-ransomware-malware-analysis",
    "date": "2023-02-14",
    "description": "Elastic Security has performed a deep technical analysis of the CUBA ransomware family. This includes malware capabilities as well as defensive countermeasures.",
    "author": [
      {
        "slug": "salim-bitam"
      }
    ],
    "image": "blog-thumb-coin-stacks.jpg",
    "category": [
      {
        "slug": "malware-analysis"
      }
    ],
    "tags": [
      "ref9019",
      "cuba",
      "ransomware"
    ]
  },
  "id": "security_labs_content-cuba_ransomware_malware_analysis-md",
  "type": "security_labs_content"
}
