{
  "attributes": {
    "raw": {
      "document": "---\ntitle: \"ICEDID Configuration Extractor\"\nslug: \"icedid-configuration-extractor\"\ndate: \"2022-12-06\"\nsubtitle: \"Configuration extraction tool for ICEDID malware.\"\ndescription: \"Python script to extract the configuration from ICEDID samples.\"\nauthor:\n  - slug: elastic-security-labs\nimage: \"tools-image.jpg\"\ncategory:\n  - slug: tools\ntags:\n  - icedid\n  - ref1021\n---\n\nPython script to extract the payload from ICEDID samples.\n\n[Download icedid-configuration-extractor.tar.gz](https://assets.contentstack.io/v3/assets/bltefdd0b53724fa2ce/blt95ce19ae8cffda29/6351abcf20f42038fb989fae/icedid-config-extractor.tar.gz)\n\n> For information on the ICEDID malware and network infrastructure, check out the following resources:\n>\n> - [ICEDIDs network infrastructure is alive and well](https://www.elastic.co/security-labs/icedids-network-infrastructure-is-alive-and-well)\n> - [ICEDID network infrastructure checking utility](https://assets.contentstack.io/v3/assets/bltefdd0b53724fa2ce/bltb86bffd1aef20c5b/6351aba34e565f1cdce29da5/icedid-checker.tar.gz)\n\n## Getting started\n\n### Docker\n\nThe recommended and easiest way to get going is to use Docker. From the directory this README is in, you can build a local container.\n\n```\ndocker build . -t icedid_loader_config_extractor\n```\n\nThen we run the container with the -v flag to map a host directory to the docker container directory.\n\n```\ndocker run -ti --rm -v $(pwd)/data:/data icedid_loader_config_extractor:latest --help\n```\n\n### Running it locally\n\nAs mentioned above, Docker is the recommended approach to running this project, however you can also run this locally. This project uses [Poetry](https://python-poetry.org/) to manage dependencies, testing, and metadata. If you have Poetry installed already, from this directory, you can simply run the following commands to run the tool. This will setup a virtual environment, install the dependencies, activate the virtual environment, and run the console script.\n\n```\npoetry lock\npoetry install\npoetry shell\npoetry lock\npoetry install\npoetry shell\nicedid_loader_config_extractor --help\n```\n\n## Usage\n\nAll samples need to be unpacked prior to execution extraction attempts.\n\nWe can either specify a single sample with **-f** option or a directory of samples with **-d**.\n\n```\ndocker run -ti --rm -v $(pwd)/data:/data icedid_loader_config_extractor:latest -d \"C:\\tmp\\samples\"\n```\n\n![ICEDID configuration extractor](/assets/images/icedid-configuration-extractor/196841115-5a3a0d95-8df4-45c2-9baa-264cfa9530e9.jpg)\n\nYou can collect the extracted configurations from the directory you set when running the extractor.\n"
    },
    "title": "ICEDID Configuration Extractor",
    "slug": "icedid-configuration-extractor",
    "subtitle": "Configuration extraction tool for ICEDID malware.",
    "date": "2022-12-06",
    "description": "Python script to extract the configuration from ICEDID samples.",
    "author": [
      {
        "slug": "elastic-security-labs"
      }
    ],
    "image": "tools-image.jpg",
    "category": [
      {
        "slug": "tools"
      }
    ],
    "tags": [
      "icedid",
      "ref1021"
    ]
  },
  "id": "security_labs_content-icedid_configuration_extractor-md",
  "type": "security_labs_content"
}
