{
  "attributes": {
    "raw": {
      "document": "---\ntitle: \"Elastic publishes 2024 Global Threat Report\"\nslug: \"elastic-publishes-2024-gtr\"\ndate: \"2024-10-01\"\ndescription: \"Elastic Security Labs has released the 2024 Elastic Global Threat Report, surfacing the most pressing threats, trends, and recommendations to help keep organizations safe for the upcoming year.\"\nauthor:\n  - slug: devon-kerr\nimage: \"2024-gtr.png\"\ncategory:\n  - slug: reports\ntags:\n  - gtr\n---\n\n*Elastic Security Labs discovers that threat actors are taking advantage of readily available and commonly abused security tools, and misconfigured environments.*\n\nElastic Security Labs has released the [2024 Elastic Global Threat Report](http://www.elastic.co/blog/elastic-global-threat-2024), surfacing the most pressing threats, trends, and recommendations to help keep organizations safe for the upcoming year. Threat actors are finding success from the use of offensive security tools (OSTs), a misconfiguration of cloud environments, and a growing emphasis on Credential Access. This report explores key telemetry from over a billion data points with emphasis on malware trends, adversary tactics, cloud security, and generative AI curated by Elastic Security Labs.\n\nRead the [announcement](http://www.elastic.co/blog/elastic-global-threat-2024) and [download](https://www.elastic.co/resources/security/report/global-threat-report) the 2024 Elastic Global Threat Report to gain an in-depth understanding of the threat landscape. "
    },
    "title": "Elastic publishes 2024 Global Threat Report",
    "slug": "elastic-publishes-2024-gtr",
    "date": "2024-10-01",
    "description": "Elastic Security Labs has released the 2024 Elastic Global Threat Report, surfacing the most pressing threats, trends, and recommendations to help keep organizations safe for the upcoming year.",
    "author": [
      {
        "slug": "devon-kerr"
      }
    ],
    "image": "2024-gtr.png",
    "category": [
      {
        "slug": "reports"
      }
    ],
    "tags": [
      "gtr"
    ]
  },
  "id": "security_labs_content-elastic_publishes_2024_gtr-md",
  "type": "security_labs_content"
}
